{
    "keep": {
        "days": true,
        "amount": 30
    },
    "auditLog": "D:\\YODO Projects\\node-base-app\\node-base-app\\logs\\debug\\.632a7ec7c31c98485024518ce605a046131ebd4c-audit.json",
    "files": [
        {
            "date": 1763991497280,
            "name": "D:\\YODO Projects\\node-base-app\\node-base-app\\logs\\debug\\debug-2025-11-24.log",
            "hash": "8637ed6a212b74ee1e4e2ceb92488d31d4a8c1a140ee457c820997315e59dde9"
        },
        {
            "date": 1764049592449,
            "name": "D:\\YODO Projects\\node-base-app\\node-base-app\\logs\\debug\\debug-2025-11-25.log",
            "hash": "1d68af731927ecb7c9d96a6e70dd787ebf1099c1cebd5cca1eb55d27982215c6"
        }
    ],
    "hashType": "sha256"
}